bitbucketopenapi/__init__.py
bitbucketopenapi/api_client.py
bitbucketopenapi/configuration.py
bitbucketopenapi/exceptions.py
bitbucketopenapi/rest.py
bitbucketopenapi/api/__init__.py
bitbucketopenapi/api/addon_api.py
bitbucketopenapi/api/branching_model_api.py
bitbucketopenapi/api/branchrestrictions_api.py
bitbucketopenapi/api/commits_api.py
bitbucketopenapi/api/commitstatuses_api.py
bitbucketopenapi/api/default_api.py
bitbucketopenapi/api/deploy_api.py
bitbucketopenapi/api/deployments_api.py
bitbucketopenapi/api/downloads_api.py
bitbucketopenapi/api/issue_tracker_api.py
bitbucketopenapi/api/pipelines_api.py
bitbucketopenapi/api/projects_api.py
bitbucketopenapi/api/properties_api.py
bitbucketopenapi/api/pullrequests_api.py
bitbucketopenapi/api/refs_api.py
bitbucketopenapi/api/repositories_api.py
bitbucketopenapi/api/search_api.py
bitbucketopenapi/api/snippet_api.py
bitbucketopenapi/api/snippets_api.py
bitbucketopenapi/api/source_api.py
bitbucketopenapi/api/ssh_api.py
bitbucketopenapi/api/teams_api.py
bitbucketopenapi/api/users_api.py
bitbucketopenapi/api/webhooks_api.py
bitbucketopenapi/models/__init__.py
bitbucketopenapi/models/account.py
bitbucketopenapi/models/account_all_of.py
bitbucketopenapi/models/account_all_of_links.py
bitbucketopenapi/models/account_all_of_links_avatar.py
bitbucketopenapi/models/author.py
bitbucketopenapi/models/author_all_of.py
bitbucketopenapi/models/base_commit.py
bitbucketopenapi/models/base_commit_all_of.py
bitbucketopenapi/models/base_commit_all_of_summary.py
bitbucketopenapi/models/branch.py
bitbucketopenapi/models/branching_model.py
bitbucketopenapi/models/branching_model_all_of.py
bitbucketopenapi/models/branching_model_all_of_branch_types.py
bitbucketopenapi/models/branching_model_all_of_development.py
bitbucketopenapi/models/branching_model_settings.py
bitbucketopenapi/models/branching_model_settings_all_of.py
bitbucketopenapi/models/branching_model_settings_all_of_branch_types.py
bitbucket_openapi-0.1.190913.dist-info/METADATA
bitbucket_openapi-0.1.190913.dist-info/WHEEL
bitbucket_openapi-0.1.190913.dist-info/top_level.txt
bitbucket_openapi-0.1.190913.dist-info/RECORD
